examples/LS96SDE.py
examples/__init__.py
hints/__init__.py
hints/hints.py
hints/utils/__init__.py
hints/utils/visualization.py
hints_kmcs-0.1.2.dist-info/LICENSE
hints_kmcs-0.1.2.dist-info/METADATA
hints_kmcs-0.1.2.dist-info/WHEEL
hints_kmcs-0.1.2.dist-info/top_level.txt
hints_kmcs-0.1.2.dist-info/RECORD
