Metadata-Version: 2.1
Name: hints-kmcs
Version: 0.1.2
Summary: A package for calculating pairwise and higher-order interactions of N-dimensional state variables from measured time series
Home-page: https://github.com/aminakhshi/hints
Author: Amin Akhshi
Author-email: amin.akhshi@gmail.com
License: UNKNOWN
Platform: UNKNOWN
Classifier: Development Status :: 3 - Alpha
Classifier: Intended Audience :: Science/Research
Classifier: Topic :: Scientific/Engineering :: Mathematics
Classifier: License :: OSI Approved :: MIT License
Classifier: Programming Language :: Python :: 3
Classifier: Programming Language :: Python :: 3.8
Classifier: Programming Language :: Python :: 3.9
Requires-Python: >=3.8.1
Requires-Dist: tqdm
Requires-Dist: ipykernel
Requires-Dist: numpy
Requires-Dist: pandas
Requires-Dist: jitcsde
Requires-Dist: sympy
Requires-Dist: matplotlib
Requires-Dist: seaborn
Requires-Dist: scikit-image
